docs/.gitkeep
docs/index.md
docs/installation.md
docs/redoc.md
docs/assets/fonts/GoodSans-Medium.otf
docs/assets/fonts/GoodSans-MediumItalic.otf
docs/assets/fonts/GoodSans-Regular.otf
docs/assets/fonts/GoodSans-RegularItalic.otf
docs/assets/images/node.png
docs/client/api.md
docs/client/asset.md
docs/client/asset_collection.md
docs/client/geospatial.md
docs/client/model.md
docs/client/node.md
docs/client/record_collection.md
docs/client/run.md
docs/client/scenario.md
docs/client/technology.md
docs/data-coverage/power/assets.md
docs/data-coverage/power/generation.md
docs/data-coverage/steel/index.md
docs/stylesheets/extra.css
feo/client/__init__.py
feo/client/asset.py
feo/client/auth.py
feo/client/constants.py
feo/client/factory.py
feo/client/geospatial.py
feo/client/model.py
feo/client/node.py
feo/client/publisher.py
feo/client/record.py
feo/client/run.py
feo/client/scenario.py
feo/client/source.py
feo/client/technology.py
feo/client/utils.py
feo/client/api/__init__.py
feo/client/api/aliases.py
feo/client/api/assets.py
feo/client/api/base.py
feo/client/api/client.py
feo/client/api/constants.py
feo/client/api/geospatial.py
feo/client/api/models.py
feo/client/api/nodes.py
feo/client/api/publishers.py
feo/client/api/records.py
feo/client/api/runs.py
feo/client/api/scenarios.py
feo/client/api/schemas.py
feo/client/api/sources.py
feo/client/api/technologies.py
feo/client/cli/__init__.py
feo/client/cli/auth.py
feo/client/cli/cli.py
feo/client/core/__init__.py
feo/client/core/logging.py
notebooks/.gitkeep
tests/.gitkeep
tests/__init__.py
tests/CI/__init__.py
tests/CI/conftest.py
tests/CI/test_api_aliases_get.py
tests/CI/test_api_provenance.py
tests/CI/test_api_records.py
tests/CI/test_api_technology.py
tests/CI/test_asset.py
tests/CI/test_asset_collection_construction.py
tests/CI/test_model.py
tests/CI/test_model_api.py
tests/CI/test_node.py
tests/CI/test_record.py
tests/CI/test_run.py
tests/CI/test_run_api.py
tests/CI/test_scenario.py
tests/CI/test_scenario_api.py
feo_client-0.0.4.dist-info/LICENSE
feo_client-0.0.4.dist-info/METADATA
feo_client-0.0.4.dist-info/WHEEL
feo_client-0.0.4.dist-info/entry_points.txt
feo_client-0.0.4.dist-info/top_level.txt
feo_client-0.0.4.dist-info/RECORD
