Metadata-Version: 2.1
Name: feo-client
Version: 0.0.4
Summary: A Python Client for programmatic interactions with the Future Energy Outlook platform by TransitionZero
Author-email: Lucas Kruitwagen <lucas.kruitwagen@gmail.com>
License: Apache License
Project-URL: Homepage, https://github.com/transition-zero/feo-client
Project-URL: Bug Reports, https://github.com/transition-zero/feo-client/issues
Project-URL: Funding, https://transitionzero.org
Project-URL: Source, https://github.com/transition-zero/feo-client
Keywords: energy,systems
Classifier: Development Status :: 3 - Alpha
Requires-Python: >=3.10
License-File: LICENSE
Requires-Dist: pandas >2
Requires-Dist: pydantic >2
Requires-Dist: requests >=2.31
Requires-Dist: httpx >0.25
Requires-Dist: click >8.1
Requires-Dist: shapely
Provides-Extra: dev
Requires-Dist: pre-commit ; extra == 'dev'
Requires-Dist: black ; extra == 'dev'
Requires-Dist: pytest ; extra == 'dev'
Requires-Dist: pytest-order ; extra == 'dev'
Requires-Dist: pytest-asyncio ; extra == 'dev'
Requires-Dist: pytest-cov ; extra == 'dev'
Requires-Dist: mypy ; extra == 'dev'
Requires-Dist: tox ; extra == 'dev'
Requires-Dist: coverage ; extra == 'dev'
Requires-Dist: types-requests ; extra == 'dev'
Requires-Dist: pandas-stubs ; extra == 'dev'
Provides-Extra: geo
Requires-Dist: geopandas ; extra == 'geo'
